{
  "DENEZY": {
    "Propriétaires": [
      "Chambaz, François",
      "Chambaz, Jules",
      "Chambaz, Rosine, veuve",
      "Crisinel, Charles-Louis",
      "Deppierraz, Constant",
      "Deppierraz, J.-Jules"
    ],
    "Rentiers": [
      "Crisinel, C.-Louis",
      "Chambaz, Rodolphe",
      "Chambaz, François",
      "Chambaz, Jules",
      "Chambaz, Alphonse"
    ],
    "Scierie": [
      "Maïer, Paul"
    ],
    "Sociétés": [
      "Société des chemins de dévestiture. R",
      "Société de la fromagerie. R"
    ],
    "Tailleur": [
      "Durussel, Adolphe"
    ],
    "Téléphoniste": [
      "Deppierraz, Eugène"
    ]
  },
  "DOMPIERRE": {
    "Autorités communales": [
      "Besson, Henri",
      "Janin, Jules",
      "Corthésy, Justin",
      "Besson, Héli",
      "Corthésy, Jean-Daniel",
      "Duc, Jaques-Félix",
      "Tenthorey, François",
      "Corthésy, Lucien",
      "Besson, Emile",
      "Badoux, Alfred",
      "Gentil, Emile"
    ],
    "Apiculteur": [
      "Corthésy, d'Héli"
    ],
    "Bétail (march.)": [
      "Corthésy, Emile",
      "Corthésy, Jules",
      "Tenthorey, François"
    ],
    "Bois (march.)": [
      "Jaton, Auguste. R"
    ],
    "Boulanger": [
      "Besson, Jean-Jules. R"
    ],
    "Café": [
      "Hofer, Jules"
    ],
    "Charpentiers": [
      "Bovat, Jean",
      "Dizerens, Paul"
    ],
    "Chef de section": [
      "Corthésy, Justin"
    ],
    "Cordonnier": [
      "Durussel"
    ],
    "Dépositaire postal": [
      "Corthésy, Jean"
    ],
    "Epicerie, mercerie et tabacs": [
      "Badoux-Buttet, Jeannette. R",
      "Besson, Jean-Jules. R",
      "Troillet, Ida"
    ],
    "Ferblantier": [
      "Thonney"
    ],
    "Fermiers": [
      "Germond, Félix",
      "Jaton, Pierre",
      "Mottet, frères",
      "Tenthorey, Aimé"
    ],
    "Fourches et râteaux (fabr)": [
      "Corthésy, Jules"
    ],
    "Inspecteur du bétail": [
      "Corthésy, François-Louis"
    ],
    "Instituteurs": [
      "Janin, Jules",
      "Corthésy, Emmy"
    ],
    "Machine à battre le grain (à vap)": [
      "Hoirie de Corthésy, Jules, aux Granges"
    ],
    "Maçons": [
      "Badoux, Eugène",
      "Badoux, Julien"
    ],
    "Maréchal": [
      "Besson, Henri"
    ],
    "Menuisiers": [
      "Corthésy, François",
      "Diserens, Paul"
    ],
    "Pasteur": [
      "Duquesne, Philippe"
    ],
    "Propriétaires": [
      "Besson, Auguste",
      "Besson, François",
      "Besson, Louis",
      "Clot, Edouard",
      "Clot, Emile",
      "Clot, François",
      "Corthésy, Ernest-Ulysse",
      "Corthésy, Jean-Daniel",
      "Corthésy, Justin",
      "Corthésy, Samuel",
      "Dind, Jules",
      "Duc, Jaques",
      "Gentil, Félix-Emmanuel",
      "Gentil, Louis",
      "Tenthorey, Aloïs",
      "Tenthorey, Emile",
      "Tenthorey, Philippe, dit François"
    ],
    "Scieur": [
      "Badoux, Ulysse"
    ],
    "Sellier": [
      "Gilliéron"
    ],
    "Sociétés": [
      "Société du battoir à blé",
      "Société de fromagerie. R",
      "Société de scierie à vapeur. R",
      "Syndicat agricole. R",
      "Société de la fromagerie des Granges. R"
    ],
    "Tailleur": [
      "Badoux, Henri",
      "Corthésy, Alcide"
    ],
    "Tailleuses": [
      "Besson. Aline",
      "Paccaud, Elise"
    ],
    "Téléphone": [
      "Bureau des postes"
    ],
    "Tonnelier": [
      "Tenthorey, François"
    ]
  },
  "FOREL-SUR-LUCENS": {
    "Autorités communales": [
      "Pidoux, Alcide",
      "Rey, Emile",
      "Pidoux, Jean-François",
      "Briod, Constant",
      "Pidoux, Louis",
      "Pidoux, Ulysse, de François",
      "Pidoux, Ulysse, de Louis",
      "Pidoux, Alexis",
      "Briod, Louis-Emile",
      "Briod, Léon",
      "Briod, Louis",
      "Pidoux, Justin"
    ],
    "Apiculteur": [
      "Briod, Louis-Emile"
    ],
    "Charretiers": [
      "Pidoux, Louis et Henri"
    ],
    "Commission scolaire": [
      "Rey, Emile",
      "Pidoux, Ulysse, de Louis",
      "Pidoux, Alexis"
    ],
    "Cordonnier": [
      "Pidoux, Henri"
    ],
    "Fermier": [
      "Schenk, Christian"
    ],
    "Inspecteur du bétail": [
      "Pidoux-Lagnaz, Jean-François"
    ],
    "Instituteur": [
      "Durussel, Emile"
    ],
    "Maréchal": [
      "Gottraux, Jules"
    ],
    "Menuisier": [
      "Briod, Abram-Daniel"
    ],
    "Pierriste": [
      "Rey, Adèle"
    ],
    "Propriétaires": [
      "Pidoux, Louis-Rodolphe",
      "Pidoux-Veyre, Jean"
    ],
    "Sociétés": [
      "Société de la fromagerie. R",
      "Société du battoir à grains. R"
    ],
    "Tailleur": [
      "Pidoux, François"
    ],
    "Tailleuse": [
      "Pidoux, Méry"
    ],
    "Téléphoniste": [
      "Rey, Emile"
    ],
    "Tisserand": [
      "Pidoux, Jean-Samuel"
    ]
  },
  "HERMENCHES": {
    "Autorités communales": [
      "Fiaux, E.",
      "Jayet, John",
      "Chalet, Jules",
      "Jayet, Constant",
      "Gavillet, E.",
      "Fiaux, Félix",
      "Fiaux, Théo"
    ]
  }
}