{
  "ORMONT-DESSUS": {
    "Charpentiers": [
      "Perretten, Jean-Théophile",
      "Perretten, Alexis",
      "Pernet, Eugène"
    ],
    "Chef de section": [
      "Favre, Vincent"
    ],
    "Cigares et tabacs": [
      "Buchs, Fritz",
      "Guiger, veuve",
      "Lœtscher-Blum",
      "Moulin, Alexis",
      "Nicollier, Ami",
      "Pernet-Pichard, Julie",
      "Perreten-Moulin, Victor"
    ],
    "Commission scolaire": [
      "Divorne, Paul",
      "Busset, Eugène",
      "Pichard-Jordan, François",
      "Moillen, Constant",
      "Pichard-Aviolat, François"
    ],
    "Cordonniers": [
      "Dutoit, Henri",
      "Führer, Abram",
      "Moulin, Henri-Alexis",
      "Pernet, David-Frédéric"
    ],
    "Couturières": [
      "Isabel, Louise",
      "Moillen-Nicollier, Marie",
      "Nicollier, Marie",
      "Perrod, Marianne",
      "Treina, Adèle"
    ],
    "Epiciers": [
      "Dupertuis, Samuel",
      "Girod, Constant",
      "Gyger, veuve",
      "Lœtscher-Blum, Maria-Louise",
      "Moulin, H.-Alexis. R.",
      "Nicollier, Ami",
      "Perreten-Moulin, Victor",
      "Pernet, Julie",
      "Pernet-Steffen, Lucie",
      "Pichard, Auguste",
      "Schneiter, Arthur"
    ],
    "Etoffes": [
      "Dupertuis, Samuel",
      "Girod, Constant",
      "Lœtscher-Blum",
      "Moulin, Alexis",
      "Pernet-Steffen, Lucie",
      "Perreten-Moulin, Victor"
    ],
    "Géomètre breveté": [
      "Busset, Eug.-Alexis"
    ],
    "Horloger": [
      "Genillard, Alexandre"
    ],
    "Hôtels (maitres d') (pour l'été)": [
      "Ansermet, Sophie",
      "Buchs, Frédéric",
      "Morex-Tille",
      "Pellet, Henri",
      "Perrochon, L."
    ],
    "Inspecteurs du bétail": [
      "Berruex, Jean",
      "Jaquerod, Vincent"
    ],
    "Instituteurs": [
      "Moillen, Jean",
      "Seyte",
      "Mani, Charles",
      "Chapalay, Constant",
      "Gilland, Théophile"
    ],
    "Institutrice": [
      "Meylan, Melanie"
    ],
    "Justice de paix": [
      "Pernet, Jean-Louis",
      "Busset, Emile",
      "Nicollier, Alexandre",
      "Favre-Jaquerod, Vincent",
      "Pichard-Moillen, Henri",
      "Pichard-Pernet, Henri"
    ],
    "Maçon": [
      "Favre, David"
    ],
    "Maréchaux": [
      "Ansermet, Auguste",
      "Favre, Jean-Alexandre",
      "Pichard, David-Alex",
      "Rey, Jérémie",
      "Nicollier, Ami",
      "Fromentin, Auguste"
    ],
    "Menuisiers": [
      "Ansermoz, Aug.-Franç.",
      "Hauswirth, Philippe-Félix",
      "Moulin, Eugène",
      "Rieben, Pierre",
      "Schäffer, Emmanuel"
    ],
    "Mercerie": [
      "Lœtscher-Blum, Maria-Louise",
      "Moulin, Henri-Alexis. R.",
      "Girod, Constant",
      "Dupertuis, Samuel",
      "Perreten-Moulin, Victor",
      "Pernet-Pichard, Julie",
      "Schneiter, Arthur"
    ],
    "Notaire": [
      "Busset, Eugène-Alexis"
    ],
    "Officier d'état civil": [
      "Pernet, Eugène",
      "Busset, Emile"
    ],
    "Pasteurs": [
      "Divorne, Paul",
      "de la Harpe, Eugène"
    ],
    "Pensions d'été": [
      "Ansermet, Sophie",
      "Busset, Alfred",
      "Busset, Augustine",
      "Pernet, Julie"
    ],
    "Quincaillerie": [
      "Dupertuis, Samuel",
      "Moulin, Alexis",
      "Perreten-Moulin, Victor"
    ],
    "Sage-femme": [
      "Favre, Marie"
    ],
    "Scieurs": [
      "Busset, Eugène",
      "Moillen, Vincent",
      "Mottier, David",
      "Treina, Eug."
    ],
    "Sociétés": [
      "Société du Stand des Diablerets",
      "Association immobilière des Jeans",
      "Fromagerie des Diablerets",
      "Société du Cordon vert",
      "Société du Cordon rouge et vert",
      "Syndicat agricole des Diablerets",
      "Fromagerie du Plan",
      "Société militaire de tir aux Armes de Guerre",
      "Société du Landsturm",
      "Société de chant « l'Echo des Diablerets »",
      "L'Union musicale des Diablerets",
      "L'Instrumentale des Diablerets"
    ],
    "Télégraphiste": [
      "Gallaz, Emmanuel"
    ],
    "Tisserands": [
      "Fromentin, Louise",
      "Motier, Rose",
      "Nicolier, Marianne",
      "Jordan, Aline",
      "Culand, Louise"
    ],
    "Divers": [
      "Favre-Jaquerod, Vincent",
      "Isabel, Vincent",
      "Nicolier, Jean-Louis",
      "Nicolier, David-Alexandre"
    ]
  },
  "RENNAZ": {
    "Autorités communales": [
      "Chausson-Loup",
      "Chatelan, Jean-Pierre"
    ],
    "Syndic": [
      "Schenk, Auguste"
    ],
    "Municipaux": [
      "Dumusc",
      "Chatelan",
      "E. Cosandey",
      "A. Dumusc."
    ],
    "Aubergistes": [
      "Chatelan, Edouard",
      "Dulon, Henri. T."
    ],
    "Couture (maitresse de)": [
      "Dumusque, Eugénie"
    ],
    "Epicerie et tabacs": [
      "Dumusque, Eug."
    ],
    "Instituteur": [
      "Diserens, Benjamin"
    ],
    "Laitiers": [
      "Bonjour, hoirie",
      "Falquier, Aloïs"
    ],
    "Meunier": [
      "Genton, Maurice"
    ],
    "Notaire": [
      "Chausson-Loup, Louis"
    ]
  }
}