{
  "LAUSANNE": {
    "ÉPICIERS": [
      "Ramelli, A.",
      "Recordon, Elisa",
      "Regamey, Nanette",
      "Regamey, Auguste",
      "Regamey, Jeannette",
      "Reverchon, L.",
      "Rey, Joseph",
      "Rochat-Reymond, C.",
      "Rohrer, demoiselle",
      "Ruedi, Charles",
      "Rupff, Samuel",
      "Sandoz, Paul",
      "Schmid, Fritz",
      "Schmidt-Frey, veuve",
      "Schwaiger-Werner, dame",
      "Simond fils, A., & E.",
      "Société coopérative de consommation",
      "Soulier, Louise",
      "Stehlin, Jaques",
      "Sudan, Raymond",
      "Syndicat des consommateurs",
      "Tenthorey, F.",
      "Thuillard, veuve",
      "Trafelet, Anna, veuve",
      "Tomei, Susanne",
      "Tschumy & Badoux",
      "Vittoz, Adrien",
      "Wäber-Stark, Babette",
      "Winandy, hoirs",
      "Winandy, Oscar",
      "Wutrich, Christian",
      "Zappa, Marie",
      "Zingre, Esther"
    ],
    "ÉPURATION A VAPEUR": [
      "Perret, J.-M.",
      "Perrin frères"
    ],
    "ÉQUARISSEUR": [
      "Jaquerod, Henri"
    ],
    "ESSENCE DE CAFÉ ET CAFÉ DE FIGUES (fabriques de)": [
      "Cerez frères",
      "Gavillet, Henri",
      "Meystre - Jaquier, Marie"
    ],
    "ÉTAT CIVIL": [
      "Rossier, A."
    ],
    "FABRIQUE DE CIRAGE": [
      "Blanc, Charles"
    ],
    "FARINES, GRAINES ET CÉRÉALES": [
      "Agence agricole vaudoise",
      "Aguet, François",
      "Beyeler, Rodolphe",
      "Christin, logic",
      "Eparvier frères",
      "Grellet, Georges",
      "Henny, frères",
      "Lob, Louis",
      "Martin fils, L., & Gowthorpe",
      "Meigniez frères",
      "Sandoz, Paul",
      "Tenthorey, F.",
      "Thuillard, veuve"
    ],
    "FERBLANTIERS": [
      "Andenmatten frères",
      "Bischoff-Will, Columban",
      "Brändli, Hector",
      "Braun, Ernest",
      "Christin, Marc",
      "Cornu, Louis",
      "Dayer-Regamey, Jos.",
      "Delisle, Emile",
      "Diaceri, Joseph",
      "Diaceri, Jules",
      "Fehlmann, Jean",
      "Felber, Gustave",
      "Heer-Tobler, Jean-Jaques"
    ]
  }
}