{
  "SAINTE-CROIX": {
    "Gypsiers et peintres": [
      "Andréni & Jaccard",
      "Demartini Maurice",
      "Jaccard César",
      "Ottone Antoine",
      "Regazzi Louis"
    ],
    "Hôtels": [
      "Hôtel d'Espagne",
      "Hôtel de France",
      "Hôtel du Jura",
      "Hôtel du Mont-Blanc"
    ],
    "Hôtels et pensions d'été et d'hiver": [
      "Bornand Emma",
      "Grand Hôtel des Rasses",
      "Hôtel - pension Beau-Séjour",
      "Hôtel Beau-Site",
      "Hôtel Beau-Regard",
      "Hôtel Mont-Fleury",
      "Hôtel-pension Muller Conrad",
      "Chalet de la Forêt",
      "Cuendet-Geneux Ami",
      "Joseph Ami",
      "Junod Alfred",
      "Pension Renaissance"
    ],
    "Imprimeur": [
      "Jeanrichard Georges"
    ],
    "Inspecteurs du bétail": [
      "Margot Louis",
      "Jaccard Emile"
    ],
    "Instituteurs": [
      "Gueissaz Paul",
      "Jaccard Emile",
      "Jaccard Robert",
      "Pahud Emile",
      "Guignard Clovis"
    ],
    "Institutrices": [
      "Besse Bertha",
      "Boullard Adèle",
      "Campiche Jenny",
      "Clerc Elisabeth",
      "Frossard Louise",
      "Gueissaz-Blanchard Cécile",
      "Gueissaz, dame",
      "Jaccard Rosa",
      "Junod-Junod Bertha",
      "Mutrux-Lagnaz Jenny",
      "Petter-Junod Mathilde",
      "Wütrich-Margot Emma"
    ],
    "Jardinier-horticulteur": [
      "Jaccard Charles"
    ],
    "Journal": [
      "Journal du district de Grandson et Feuille d'Avis de Ste-Croix"
    ],
    "Justice de paix": [
      "Junod Constant",
      "Campiche Louis",
      "Champod Jules",
      "Delay Arthur",
      "Bornand Armand",
      "Jaccard-Recordon Emile",
      "Simon Jules"
    ],
    "Laine de bois": [
      "Jaccard frères"
    ],
    "Librairie-papeterie": [
      "Bornand Anna"
    ],
    "Lingères": [
      "Jeanrenaud Marie",
      "Junod Sara"
    ],
    "Lunetiers": [
      "Jaccard Albert",
      "Mutrux F.-A."
    ],
    "Maréchal": [
      "Lardelli Edouard"
    ],
    "Mécanique (école de petite)": [
      "Kempin Richard"
    ],
    "Médecins": [
      "Descombaz Henri",
      "Nicolet Victor"
    ],
    "Menuisiers-charpentiers": [
      "Bornand Samuel",
      "Gloor John",
      "Jaccard Alfred",
      "Mouquin Louis",
      "Muller Jacob",
      "Thévenaz Adrien"
    ],
    "Menuisiers-ébénistes": [
      "Mutrux Henri",
      "Jaques Arthur"
    ]
  }
}