{
  "VILLE DE MORGES": {
    "Pasteurs.": [
      "Bergier Rodolphe",
      "Bovon Eugène",
      "Henrioud Alexis",
      "Pelichet Gustave",
      "Meyland Aug.",
      "Secretan Gustave"
    ],
    "Pêcheurs,": [
      "Berthold Charles",
      "Berthold Jules",
      "Mariot Marius",
      "Ramuz Henri",
      "Vincent Louis"
    ],
    "Pédicure.": [
      "Grisel E."
    ],
    "Peintre-artiste.": [
      "Giron Charles"
    ],
    "Peintres en voitures.": [
      "Jaccoud veuve & fils"
    ],
    "Pensionnats de demoiselles.": [
      "Bonzon",
      "Brindeau Maria",
      "Cauderay-Dolleyres",
      "Gagg Henriette",
      "Jaccard Elisabeth",
      "Meylan Aug.",
      "Morgenroth Cecile",
      "Richardet Alice",
      "Thomas Fanny",
      "Vittoz"
    ],
    "Pensionnats de jeunes gens.": [
      "Barblan Jacob",
      "Le Roy Ernest-Louis"
    ],
    "Pharmaciens.": [
      "Buenzod Benjamin",
      "Cuérel Alfred",
      "Soutter Albert"
    ],
    "Potographe.": [
      "Thibault Georges"
    ],
    "Photographie (fournitures pour).": [
      "Thibault, Georges"
    ],
    "Pianos (fabr. de).": [
      "Passard E."
    ],
    "Poêliers.": [
      "Von Auw Henri",
      "Barmaverain Joseph",
      "Guala Paul"
    ],
    "Poids et mesures (vérificateurs des).": [
      "Baumann Alfred"
    ],
    "Police (commissaire de).": [
      "Kahn Charles"
    ],
    "Pompes à incendie.": [
      "Salathé frères"
    ],
    "Poste.": [
      "Bataillard Charles"
    ],
    "Poterie.": [
      "Cornu-Croisier C.",
      "Cristin Louise",
      "Demenga Rodolphe",
      "Meyer M. & S.",
      "Moraz Charles",
      "Wenger sœurs"
    ],
    "Poudre (dépôt de).": [
      "Jaccoud, veuve & fils"
    ],
    "Préposé aux inhumations.": [
      "Wenger Emile"
    ],
    "Préposé aux poursuites et faillites.": [
      "Dombald Henri"
    ],
    "Professeurs au Collège.": [
      "Barblan Jacob",
      "Béraneck Jules",
      "Friderici Victor",
      "Gaillard Ami",
      "Henchoz Louis",
      "Rupfer Emile",
      "Leyvraz H.",
      "Reymond Lucien",
      "Robert Florian",
      "Scheibler Fritz",
      "Vittel Berthe",
      "Vittel Max",
      "Warnery Marthe"
    ],
    "Professeurs de musique.": [
      "Curchod",
      "Golay Elisa",
      "Humbert Georges",
      "Laufer Auguste",
      "Passard Emile",
      "Rehberg Frédéric",
      "Richardet Marie",
      "Rochedieu Emile",
      "Stæubi Aloïs",
      "Thury Julie",
      "Yersin Emile"
    ],
    "Professeurs de natation et de gymnastique.": [
      "Scheibler Fritz",
      "Thury Julie"
    ]
  }
}