{
  "LAUSANNE": {
    "ORGANES DE TRANSMISSIONS": [
      "Gerber Jean"
    ],
    "ORTHOPÉDISTES": [
      "Bocksberger-Rüd J.",
      "Institut orthopédique",
      "Schærer (Société anonyme)"
    ],
    "OUTILS EN BOIS, marchands de.": [
      "Durand Hector"
    ],
    "OUTILLAGE EN TOUS GENRES": [
      "Schœpperlé, Schmidt & Cie"
    ],
    "PANSEMENTS, art. de.": [
      "Union pharmaceutique romande"
    ],
    "PAPETERIES": [
      "Bergamin J.-A.",
      "Burnens & Sudheimer",
      "Chave-Rochat, dame",
      "Dérivaz A.",
      "Duvoisin-Secretan Aug.",
      "Duvoisin-Wyssa, veuve",
      "Frankfurter Ed.",
      "Gagnaux Emile",
      "Gonin J.",
      "Guye Henri",
      "Halbach A.",
      "Humbert J.",
      "Jequier Jeanne",
      "Kaiser F.",
      "Krieg Ch. & Cie",
      "Mack Edouard",
      "Marcel Emile",
      "Marchand Berthe",
      "Martinaglia M.",
      "Ottesen L. et O.",
      "Ottesen V.",
      "Payot & Cie",
      "Rabinère R.",
      "Robert frères",
      "Roussy Th.",
      "Schäufelberger R.",
      "Steiner E.",
      "Tarin Constant",
      "Turré-Hédiger Clém."
    ],
    "PAPIERS EN GROS, marchands de.": [
      "Industrie générale du papier (S.A.)",
      "Marmillon & Cie",
      "Stoucky & Cie"
    ],
    "PAPIERS PEINTS, marchands de.": [
      "Arnaud-Peterhans L.",
      "Genoud, Francis & Cie",
      "George Louis fils & Cie",
      "Gianotti Annibal",
      "Jaccard E."
    ],
    "PARAPLUIES ET OMBRELLES marchands et fabricants de": [
      "Besson Marie",
      "Besson Ephise",
      "Chanson-Clavel, Antoine",
      "Counil-Chanson, veuve",
      "Dépierraz-Maillet Marie",
      "Hunziker-Forny L."
    ],
    "PARATONNERRES construct. de.": [
      "Beck-Welty L.",
      "Droguet Ernest",
      "Fatio Ls & fils"
    ]
  }
}