{
  "FOREL sur LUCENS": {
    "Sociétés": [
      "Caisse d'assurance contre les pertes du bétail",
      "De fromagerie",
      "Du battoir à grains"
    ],
    "Téléphoniste": [
      "Juvet Nancy"
    ]
  },
  "HERMENCHES": {
    "Autorités communales": [
      "Fiaux Gabriel",
      "Jayet John"
    ],
    "Syndic": [
      "Chalet Jules"
    ],
    "Municipaux": [
      "Fiaux Henri",
      "Gavillet E.",
      "Fiaux Théodore",
      "Fiaux Victor",
      "Jayet Lucien",
      "Métraux Henri"
    ],
    "Secrétaire": [
      "Fiaux Lucien"
    ],
    "Boursier": [
      "Métraux E."
    ],
    "Agriculteurs": [
      "Becholey Rosine",
      "Besson Alexis",
      "Chalet Henri",
      "Chalet Siméon",
      "Charmoy Louis",
      "Denalet Emile",
      "Dutoit François",
      "Fiaux Emile",
      "Fiaux-Guex Samuel",
      "Fiaux L.-A.",
      "Jayet Emile",
      "Jayet Jean-Samuel",
      "Maillard Samuel",
      "Rod Adolphe"
    ],
    "Assesseur": [
      "Besson Alexis"
    ],
    "Aubergistes": [
      "Jaquier Auguste",
      "Thélin Henri"
    ],
    "Charpentier": [
      "Bulloz Héli"
    ],
    "Charron": [
      "Augsburger Emile"
    ],
    "Commission scolaire": [
      "Ruchet",
      "Métraux Henri"
    ],
    "Cordonniers": [
      "Fiaux-Mottaz Louis",
      "Jaquier Jean"
    ],
    "Epicerie, mercerie": [
      "Fiaux Clara",
      "Fiaux Victor"
    ],
    "Inspecteurs du bétail": [
      "Métraux Emile"
    ],
    "Instituteurs": [
      "Dessauges Alfred",
      "Dessauges-Bornand Clara"
    ],
    "Maréchal": [
      "Jayet Constant"
    ],
    "Poste": [
      "Chalet Alphonse"
    ],
    "Sellier": [
      "Chanez Louis"
    ],
    "Sociétés": [
      "De fromagerie",
      "Du moulin agricole du Jorat"
    ],
    "Tailleuses": [
      "Jaquier Elise",
      "Jayet Mery",
      "Morel Clara"
    ],
    "Téléphoniste": [
      "Thélin Henri"
    ],
    "Tisserand": [
      "Fiaux Emile"
    ]
  },
  "LOVATENS": {
    "Autorités communales": [
      "Léchaire Adrien",
      "Rochat Eugène"
    ],
    "Syndic": [
      "Pichonnat Fernand"
    ],
    "Municipaux": [
      "Giroud Louis",
      "Léchaire Constant",
      "Léchaire Héli",
      "Léchaire Alfred"
    ],
    "Secrétaire": [
      "Mojonnier Jules"
    ],
    "Boursier": [
      "Léchaire Adrien"
    ],
    "Agriculteurs": [
      "Centlivre Aimé",
      "Favez Jules",
      "Germond François",
      "Germond Ulysse",
      "Léchaire François",
      "Mojonnier Daniel",
      "Ogay Eugène",
      "Ogay Justin",
      "Ogay Ulysse",
      "Pasche Louis",
      "Pichonnat Eugène",
      "Pichonnat Jean"
    ],
    "Bouchers": [
      "Léchaire Ulysse",
      "Piot Louis"
    ],
    "Café": [
      "Bard Siméon"
    ],
    "Charrons": [
      "Giroud Fréd.",
      "Piot Henri"
    ],
    "Commission scolaire": [
      "Léchaire Adrien",
      "Mojonnier Jules"
    ],
    "Cordonnier": [
      "Giroud H."
    ],
    "Epicerie": [
      "Germond Emile",
      "Germond Julie"
    ],
    "Inspecteur du bétail": [
      "Léchaire Paul"
    ],
    "Instituteur": [
      "Rochat Eugène"
    ],
    "Juge de paix": [
      "Léchaire Héli"
    ],
    "Laitier": [
      "Condenserie"
    ],
    "Maçon": [
      "Pasche Jules"
    ],
    "Maréchal": [
      "Giroud Eugène"
    ],
    "Sociétés": [
      "Immobilière de la Colline",
      "De fromagerie",
      "Du battoir à blé"
    ],
    "Téléphoniste": [
      "Bard Elisa"
    ],
    "Tisserand": [
      "Giroud Louis"
    ],
    "Voiturier": [
      "Germond Emile"
    ]
  },
  "LUCENS": {
    "Autorités communales": [
      "Rey Ferdinand",
      "Wenger Em."
    ],
    "Syndic": [
      "Tanner Jean"
    ],
    "Municipaux": [
      "Gruninger Georges",
      "Trolliet Louis",
      "Genier Louis",
      "Ballif Emile"
    ],
    "Secrétaire": [
      "Bourgeois Constant"
    ],
    "Boursier": [
      "Michod Aloïs"
    ],
    "Acétylène (fabr. d')": [
      "Jornod Elie"
    ],
    "Agriculteurs": [
      "Ballif Emile",
      "Ballif Henri",
      "Bourgeois Constant",
      "Bourgeois Octave",
      "Briod M.",
      "Déglon Louis",
      "Gavillet J.",
      "Gruninger Georges",
      "Michod Constant",
      "Michod frères",
      "Pidoux L.",
      "Schneider H.",
      "Thoney L.",
      "Trolliet L."
    ],
    "Architecte": [
      "Buttet-Blanc Louis"
    ],
    "Assesseurs": [
      "Bourgeois Constant",
      "Rey Daniel-Ferdinand"
    ],
    "Auberges et cafés": [
      "Baudet-Matthys John",
      "Brasserie du Cardinal",
      "Crausaz Ulysse",
      "Holzer Joseph",
      "Jaquier Marie",
      "Maillard Auguste",
      "Pidoux Louis",
      "Savioz Henriette",
      "Scheltle Henriette",
      "Vaney Ed.",
      "Vuagniaux Rosette"
    ],
    "Bière (dépôts de)": [
      "Grande Brasserie Beauregard",
      "Favre Albert",
      "Porchet Samuel",
      "Brasserie de Moudon"
    ]
  }
}