{
  "AUBERSON": {
    "Boîtes d'écoles (fab. de).": [
      "Joseph Paul"
    ],
    "Bouchers-charcutiers": [
      "Bornand Ch.",
      "Guye César",
      "Jaccard Samuel"
    ],
    "Boulangers-pâtissiers": [
      "A. Bornand & Cie.",
      "Jaques Louis",
      "Société de consommation"
    ],
    "Bûcheron": [
      "Jaccard-Giroud Ed."
    ],
    "Cafés, cercles": [
      "Charnaux Juste",
      "Barbezat",
      "Cercle Industriel",
      "Côte Camille"
    ],
    "Charnières (fab. de).": [
      "Jaccard Numa"
    ],
    "Charpentiers-menuisiers": [
      "Gueissaz Jules",
      "Joseph Henri",
      "Joseph Paul"
    ],
    "Chaussures (mag. de).": [
      "Gonthier John",
      "Margot E. & C.",
      "Société de consommation"
    ],
    "Coiffeurs": [
      "Gueissaz Emile",
      "Jaccard Hermann"
    ],
    "Commission scolaire": [
      "Bornand-Golaz Auguste",
      "Gueissaz André",
      "Margot Etienne"
    ],
    "Cordonniers": [
      "Gonthier John",
      "Guye Paul",
      "Pantet Emile"
    ],
    "Coupe-verre (fab. de).": [
      "Jaccard Léon",
      "Reymond William"
    ],
    "Couturières": [
      "Cuendet-Joseph Ida",
      "Gueissaz Nelly",
      "Recordon Laura",
      "Recordon-Margot Rosalie"
    ],
    "Dentiste": [
      "Jaccard-Cuendet Ami"
    ],
    "Denrées coloniales": [
      "A. Bornand & Cie.",
      "Margot Et. & C."
    ],
    "Ebénistes-menuisiers": [
      "Jaccard Ele",
      "Jaques E. & Cie.",
      "Joseph Henri"
    ],
    "Encadreurs": [
      "Joseph Paul",
      "Joseph Henri"
    ],
    "Entrepreneur": [
      "Lanfranchini Rob."
    ],
    "Epicerie, mercerie": [
      "A. Bornand & Cie.",
      "Charnaux Juste",
      "Côte Camille",
      "Margot Constant",
      "Margot Et. & C.",
      "Martin-Clément Emile",
      "Société de consommation d'Auberson"
    ],
    "Fromages (gros)": [
      "Bornand & Cie.",
      "Margot Et. & C."
    ],
    "Gérances": [
      "Margot-Reymond L."
    ],
    "Inspecteur du bétail": [
      "Jaccard Emile"
    ],
    "Instituteur": [
      "Meylan Maurice"
    ],
    "Institutrices": [
      "Margot-Junod Thérèse",
      "Gonthier Marie",
      "Deriaz Marguerite"
    ],
    "Laiterie": [
      "Guye César"
    ],
    "Maçonnerie": [
      "Lanfranchini Robert"
    ],
    "Mécaniciens": [
      "Jaccard Arthur",
      "Jaccard Léon, S. A. R.",
      "Jaccard Louis",
      "Jaccard Numa"
    ],
    "Modiste": [
      "Jaques Rose"
    ],
    "Pension d'étrangers": [
      "Bornand Julie"
    ],
    "Porcs (comm. de).": [
      "Bornand-Jaccard Emile",
      "Guye César",
      "Margot Philippe"
    ],
    "Poste, télégraphe et téléphone": [
      "Bornand Arthur"
    ],
    "Quincaillerie": [
      "Martin-Clément Emile"
    ],
    "Renseignements": [
      "Margot-Reymond Louis"
    ],
    "Sage-femme": [
      "Desponds Andrée"
    ],
    "Scierie": [
      "Addor Jules"
    ],
    "Sellier": [
      "Pantet Emile"
    ],
    "Serrures": [
      "Margot J.-L."
    ],
    "Skis (fab. de).": [
      "Joseph Paul"
    ],
    "Sociétés": [
      "du Cercle industriel",
      "des Armes-Réunies",
      "Immobilière des Granges",
      "Coopérative de consommation de l'Auberson",
      "des Eaux",
      "de fromagerie",
      "de gymnastique",
      "Section de la Croix-Bleue",
      "Syndicat d'élevage",
      "Vélo-Club 1924",
      "La Jurassienne",
      "Auto-transports, S. A."
    ],
    "Tissus": [
      "Consommation"
    ],
    "Tourneur sur bois": [
      "Jaccard Aug."
    ],
    "Vins (march. de).": [
      "Bornand Charles",
      "Margot-Cuendet Ami",
      "Margot E. & Cie.",
      "Société de Consommation"
    ],
    "Vis (fab. de).": [
      "Jaccard Louis"
    ],
    "Voituriers": [
      "Auto-Transports S. A.",
      "Bornand Ch.",
      "Bornand Edouard",
      "Jaques Constant",
      "Jaccard-Thuillard Ls."
    ],
    "Courtier": [
      "Gueissaz André"
    ],
    "Echappements (cylindre)": [
      "Besse Gustave",
      "Gueissaz James"
    ],
    "Etuis et écrins": [
      "Jaccard Emile",
      "Jaques Auguste"
    ],
    "Rhabilleurs": [
      "Gueissaz James"
    ],
    "Boîtes (fab. de)": [
      "Cuendet John-E.",
      "Gueissaz André",
      "Jaccard-Thévenaz",
      "Margot-Cuendet Ami"
    ],
    "Claviers": [
      "Jaccard Louis",
      "Margot Emile",
      "Vve Margot Louis"
    ],
    "Ebénisterie": [
      "Jaccard Emile",
      "Jaques Auguste"
    ],
    "Pièces à musique (fournit. pour)": [
      "Cuendet Edouard",
      "Jaccard Louis"
    ],
    "Rhabilleur en musique": [
      "Baud Aug."
    ],
    "Rouleaux (fab. de)": [
      "Cuendet Ed.",
      "Jaccard-Winkler Jules"
    ],
    "Vis sans fin et ébauches (fab. de)": [
      "Cuendet Ed.",
      "Jaccard Louis"
    ]
  }
}