{
  "VILLE DE LAUSANNE": {
    "Ingénieurs": [
      "Michaud G.",
      "Moukheibir M.",
      "Muller H. & Dionisotti M.",
      "Muret Henri",
      "Neuhaus Ernest",
      "Neuhaus & Koch",
      "Nicod Henri",
      "Nicole Gabriel",
      "Oyex César",
      "Pache-Menet Alfred",
      "Pahud J.-D.",
      "Paris Adrien",
      "Pelet-Pittet C.",
      "Pelichet Constant",
      "Pellaton Berthold",
      "Perret Louis",
      "Petitpierre Alexis-Jean",
      "Piaget Arthur-V.",
      "Piguet Robert",
      "Piller L.",
      "Piot Emile",
      "Piot Robert",
      "Pochon Ernest",
      "Polla Robert",
      "Potterat H.",
      "Quaglia Jacques",
      "Rapin J.",
      "Rauchenstein Friedrich",
      "Rey Henri",
      "Rey Eugène",
      "Rivier Etienne",
      "Robert Adolphe",
      "Rochat-Mercier Frédéric",
      "Rochat Octave",
      "Rochat-Soutter F.",
      "Rubin & Welti",
      "Ruffy V.",
      "Ruttimann Walter",
      "Sambuc C.",
      "Sarrasin Alexandre",
      "Savary Edouard",
      "Schär Otto",
      "Schenk Paul",
      "Schindler B.",
      "Schwarz Max",
      "Simon & Cie",
      "Stuky Alfred",
      "Tschumy Adrien",
      "Vittoz André",
      "Xydis C.",
      "Zehnder A.",
      "Zuber Jules"
    ],
    "INHUMATIONS": [
      "Bureau"
    ],
    "INSIGNES": [
      "Amaron Auguste",
      "Bovay Edouard",
      "Chollet Marie"
    ],
    "INSPECTEURS DU BÉTAIL": [
      "Barraud Georges",
      "Blanc Aloïs",
      "Mischler Maurice",
      "Janin Jules",
      "Laurent Gustave",
      "Martin Jean",
      "Pache Ed."
    ],
    "INSPECTEUR DES CONSTRUCTIONS FÉDÉRALES": [
      "Bonjour Chs."
    ]
  }
}