{
  "PAYERNE": {
    "Menuisiers": [
      "Chaudet Louis",
      "Doudin Eugène",
      "Duperrex Frédéric",
      "Jomini Eugène",
      "Jomini Paul",
      "Kolly César",
      "Moser Henri",
      "Perrin Ad.",
      "Perrin-Ryser Henri",
      "Sommerer Emile"
    ],
    "Mercerie": [
      "Aux Galeries Vaudoises",
      "Bladt P.",
      "Assal-Baudet Louisa",
      "Brunschwig Philippe",
      "Cherbuin Eugénie",
      "Colomb Eugène",
      "Cuérel Auguste",
      "Ducry Ursule",
      "Jomini-Husson",
      "Goutte Antoine",
      "Gunzburger & Meyer",
      "Indermuhle Alfred",
      "Mestral & Righetti",
      "Rossier-Pahud H.",
      "Rothlisberger-Indermuhle-Roth, dame",
      "Schwab-Wintsch S.",
      "Savary-Schwab Emma",
      "Chevroulet, dame"
    ],
    "Meubles": [
      "Germond Frédéric",
      "Hermann-Savary Marie, Vve d'Edouard",
      "Kolly César",
      "Sommerer Emile"
    ],
    "Meunier": [
      "Wicht Gustave"
    ],
    "Modes": [
      "Aux Galeries Vaudoises",
      "Bladt P.",
      "Cherbuin Eugénie",
      "Otz, Dlle",
      "Spielmann M."
    ],
    "Motos": [
      "Ischy-Savary Ls.",
      "Magnenat-Caille Emile",
      "Maffiolini Jean"
    ],
    "Notaires": [
      "Bersier & Laurent",
      "Demiéville Edouard"
    ],
    "Œufs (comm. de)": [
      "Rapin-Silmo Marcel"
    ],
    "Officier d'état-civil": [
      "Matter Louis"
    ],
    "Organistes": [
      "Assal Marie",
      "Wahlen Blanche"
    ],
    "Outils agricoles (fabr.)": [
      "Liechti Albert"
    ],
    "Papeterie": [
      "Aux Galeries Vaudoises",
      "Bladt P.",
      "Clerc-Brocard Ad.",
      "Husson Jules",
      "Ischy-Savary Ls.",
      "Jomini Louis",
      "Savary-Battaini Elise",
      "Vuilleumier P.-A."
    ],
    "Parapluies": [
      "Bersier-Michaud Marcel",
      "Ischy-Savary Ls.",
      "Spielmann M.",
      "Viani Ant."
    ],
    "Parquets": [
      "Burdet Louis"
    ],
    "Pasteurs": [
      "Courvoisier Maxime",
      "Guise Hans",
      "Panchaud Paul",
      "Tripod Maurice"
    ],
    "Pâtissiers": [
      "Baumgartner Fritz",
      "Porchet Robert",
      "Guggi Robert",
      "Husson Henri",
      "Jaquier Henri",
      "Neuhaus Eugène",
      "Rossier-Groux Henri",
      "Tappy Ernest"
    ],
    "Pensionnats": [
      "Assal-Leuenberger",
      "Jomini-Decorges Ch.-Fr."
    ]
  }
}