{
  "VILLE DE LAUSANNE": {
    "AGENCE RELIGIEUSE": [
      "Baud Henri"
    ],
    "AGENCE TÉLÉGRAPHIQUE": [
      "Bonard Arnold"
    ],
    "AGENCES DE VOYAGES": [
      "Cie Intern. des Wagons-Lits",
      "Cunard Line",
      "Galland & Cie",
      "Méditerranée-Amérique, Voyages et Transports, S. A.",
      "Perrin R. & Cie",
      "Scheidegger Fréd.",
      "Suisse-Italie, S. A.",
      "Thos. Cook & Son.",
      "Tourist-Office Grand",
      "Voyages A. Kuoni, S. A."
    ],
    "AGENCES DES WAGONS-LITS": [
      "Méditerranée-Amérique, Voyages et Transports, S. A.",
      "Suisse-Italie, Société de Voyages et Transports"
    ],
    "AGENTS D'AFFAIRES PATENTÉS": [
      "Bussy Emile",
      "Chanson Robert",
      "Charbon L.",
      "Contini J.",
      "Cottens Maurice",
      "Deschamps J. & Blanc E.",
      "Dessert Alex.",
      "Garnier Olivier"
    ]
  }
}