{
  "LAUSANNE": {
    "CORDONNIERS, fournitures pour": [
      "Campiche & Rapin",
      "Filippone E.",
      "Francillon & Cie (S. A.)",
      "Monney Antoine",
      "Pellet J.",
      "Wiedmann J."
    ],
    "CORSETS": [
      "Abetel Elisabeth",
      "Baer Emile",
      "Berger A.",
      "Blanc Albertine",
      "Bocksberger Oscar",
      "Bonnard & Cie, S A.",
      "Borgeaud-Giraud E.",
      "Chevalley-Vienot, Mme",
      "Coderay Betty",
      "Degaudenzi-Auberson E.",
      "Favre Cécile",
      "Gay Eva, Dlle",
      "Grandjean Irène",
      "Kurz-Toulouse C.",
      "Manufacture Inex (S. A.)",
      "Merlin H., dame",
      "Meuwly-Chassin Valentine",
      "Perroud, dame"
    ],
    "COSTUMIERS": [
      "Michoud Ch.",
      "Müller-Hasler J.-A., dame",
      "Regamey-Dufaux Emma",
      "Vogel L., dame"
    ],
    "COTONS": [
      "Weith & Cie."
    ],
    "COURROIES DE TRANSMISSION": [
      "A l'Artisan Pratique, E. Schmidt & Cie",
      "Dufey G. & Cie.",
      "Francillon & Cie (S.A.)"
    ],
    "COURONNES MORTUAIRES": [
      "Pompes Funèbres Générales, S. A.",
      "Pompes funèbres de St-Laurent, S. A."
    ],
    "COURTEPOINTIÈRES": [
      "Asile de Béthesda",
      "Barbey G.",
      "Bellenger-Levet Jeanne",
      "Conil E.",
      "Décosterd, Mlles",
      "Gaudio François"
    ],
    "COUTELLERIE": [
      "Besson F. & A. frères, succ. d'Ephise Besson",
      "Besson Jean.",
      "Besson Stéphane.",
      "Besson-Baud Jean.",
      "Francillon & Cie (S. A.)",
      "König Ls.",
      "Kuderli J."
    ]
  }
}