{
  "TRELEX": {
    "Amodiateurs": [
      "Bory Ami",
      "Bory John",
      "Galé Auguste. R.",
      "Moinat frères"
    ],
    "Apiculteurs": [
      "Courvoisier Aimé. T.",
      "Détraz François"
    ],
    "Associations mutualistes de retraite": [
      "Courvoisier A."
    ],
    "Aubergistes": [
      "Centlivre, Vve",
      "Perrochon Ls"
    ],
    "Bétail (march. de)": [
      "Galé Aug. R."
    ],
    "Boulangerie": [
      "Eberhardt Vve. R."
    ],
    "Buraliste postal": [
      "Amiguet Elie"
    ],
    "Chef de section": [
      "Courvoisier Aimé"
    ],
    "Commission scolaire": [
      "Galé John",
      "Galé Charles",
      "Vanat Auguste"
    ],
    "Cordonniers": [
      "Détraz François",
      "Patthey Ulysse"
    ],
    "Couturières": [
      "Annen Jeanne",
      "Galé Jenny",
      "Martin Lina",
      "Vanat Adèle"
    ],
    "Entrepreneurs": [
      "Daglia-Saléro Ls. T.",
      "Dumartheray Henri"
    ],
    "Epicerie, mercerie, tabacs": [
      "Diserens Emile. T.",
      "Meystre Ch.",
      "Ravenel John. R."
    ],
    "Inspecteur du bétail": [
      "Reichenbach Louis"
    ],
    "Instituteurs": [
      "Dépassel Louis.",
      "Morel Evelyne"
    ],
    "Jardiniers": [
      "Budry Charles",
      "Galé Louis"
    ],
    "Maçon": [
      "Dumartheray Henri"
    ],
    "Maréchaux": [
      "Tecon frères"
    ],
    "Menuisier": [
      "Genoud Ernest. T."
    ],
    "Pasteur": [
      "Masson Charles"
    ],
    "Pension": [
      "La Coque"
    ],
    "Repasseuse": [
      "Galé Herminie"
    ],
    "Rentiers": [
      "Buenzod Alfred",
      "Chollet Henri",
      "Leydre Jenny",
      "Pellissier Adeline. T.",
      "Rufer sœurs"
    ],
    "Scieur": [
      "Zenger Jacob"
    ],
    "Sellier": [
      "Zaug Jules"
    ],
    "Sociétés": [
      "de laiterie. R.",
      "Laiterie de Trélex, soc. coop. R."
    ],
    "Téléphoniste": [
      "Perrochon Ls"
    ]
  },
  "VICH": {
    "Autorités communales": [
      "Forestier Frs",
      "Hügly Gustave",
      "Panchaud de Bottens Luc. T.",
      "Rossier Albert",
      "Tritten Oscar",
      "Golay Fernand",
      "Falconnier Charles",
      "Charbonnier Auguste"
    ],
    "Agriculteurs": [
      "Aubert Alfred",
      "Caboussaz Ernest. T.",
      "Fonjallaz Maurice",
      "Morax Albert",
      "Rossier Albert",
      "Tritten Oscar. T."
    ],
    "Aubergiste": [
      "Piot Marcel. T."
    ],
    "Bois": [
      "Forestier François. R."
    ],
    "Boulanger": [
      "Chevalley Henri"
    ],
    "Buraliste postal": [
      "Remund Jules"
    ],
    "Commission scolaire": [
      "Falconnier",
      "Mlle Dumas",
      "Mlle Franckfort",
      "Berthet Edouard"
    ],
    "Cordonnier": [
      "Bozonetti Joseph"
    ],
    "Epicerie": [
      "Aubert-Croisier Charles. R.",
      "Destraz Henri. R."
    ],
    "Hongreur": [
      "Falconnier Charles. T."
    ],
    "Inspecteur du bétail": [
      "Hédiger Paul"
    ],
    "Instituteurs": [
      "Pahud Emile",
      "Guex-Isoz Marcelle"
    ],
    "Pépiniériste-viticulteur": [
      "Caboussaz Ernest"
    ],
    "Pisciculture": [
      "Burnens Henri"
    ],
    "Scierie": [
      "Forestier François. RT."
    ],
    "Sellier": [
      "Favre Henri"
    ],
    "Société": [
      "Société du battoir à blé. R."
    ],
    "Tailleuse": [
      "Francfort Louise"
    ],
    "Téléphone": [
      "Auberge communale"
    ],
    "Vignerons": [
      "Hügly Gustave",
      "Pasche Henri",
      "Tappaz Jules"
    ],
    "Divers": [
      "Dumas M., Mlle"
    ]
  }
}