{
  "MONTREUX": {
    "COMMISSION SCOLAIRE": [
      "Buhrer",
      "Emery Benjamin",
      "Mercanton Félix",
      "Vuilleumier P.",
      "Monnier",
      "Nicollier Marius",
      "Tauxe-Berthex"
    ],
    "Médecin scolaire.": [
      "Fügli Gaspard"
    ],
    "Justice de paix du cercle.": [
      "(Vacat)",
      "Michel Louis",
      "Masson Eugène",
      "Barbey Maurice",
      "Perrier Victor",
      "Delapraz Ch.",
      "Mottaz Ed."
    ],
    "Juge informateur.": [
      "Sinner U.",
      "Estoppey Henri",
      "Vuillamy Robert"
    ],
    "Feu (service du).": [
      "Emery Jules",
      "Gardei Alfred",
      "Pilet Charles",
      "Mayor Ernest",
      "Zbären Aloïs"
    ],
    "Police.": [
      "Byrde David"
    ],
    "Abattoirs.": [
      "Abattoirs",
      "Mury Vincent",
      "Ravussin Henri"
    ],
    "Aciers et outils en gros.": [
      "Wixler Lucien"
    ],
    "Administration postale.": [
      "Kues Ch.",
      "Duperret Louis",
      "Faucherre",
      "Maillard E.",
      "Mamin Louis",
      "Mermod Edouard",
      "Junod-Truan Hélène",
      "Bettens",
      "Dupraz Louis",
      "Broyon L.",
      "Reutler J.",
      "Spicher C."
    ],
    "Affichage.": [
      "Société générale d'affichage"
    ],
    "Agence commerciale.": [
      "Bujard André & Co."
    ],
    "Agences immobilières.": [
      "Bujard André & Co.",
      "Vallotton A. & Furrer P."
    ],
    "Agence en douane.": [
      "Dubois frères"
    ],
    "Agence maritime.": [
      "DUBOIS FRÈRES"
    ],
    "Agence de publicité.": [
      "Publicitas"
    ],
    "Agences de voyages.": [
      "J. ALLAMAND",
      "DUBOIS FRÈRES",
      "Perret Ernest",
      "Thos Cook & Son"
    ],
    "Agents d'affaires patentés.": [
      "LOUIS CHALET",
      "JORDAN ALOIS"
    ]
  }
}