{
  "Ville de Rolle": {
    "Bouchers": [
      "Imhof Fréd.",
      "Tissot Jules"
    ],
    "Boulangers": [
      "Baud Bernard-Alfred",
      "Beck Louis",
      "Remund",
      "Rolli Benjamin"
    ],
    "Brevets d'invention": [
      "Flesch L."
    ],
    "Cafés": [
      "Bonjean-Rolaz Victor",
      "Briel-Schaffer, Veuve",
      "Dessemontet Constant",
      "Gros César",
      "Gugger Jean",
      "Henry Edgar",
      "Larpin Ferdinand",
      "Reverchon Paul",
      "Rod Emile",
      "Roth, Vve de Louis",
      "Roquerbe Henri",
      "Simond Jules",
      "Truan",
      "Spichiger Jean"
    ],
    "Café-chocolat": [
      "Widmer H."
    ],
    "Caisses (fab. de)": [
      "Arbel Arsène"
    ],
    "Cercueils": [
      "Hessenmuller-Genton-Chevallaz, (S.A.)",
      "Pfund Silas"
    ],
    "Chapelleries": [
      "Giroud-Gonthier, Vve",
      "Au Louvre, Magistris M., gérante",
      "Yersin-Rochat B."
    ],
    "Charcuteries": [
      "Trachsel Jaques",
      "Widmer Alexandre"
    ],
    "Charpentiers": [
      "Burnier Jules",
      "Pittet Paul",
      "Vionnet Auguste"
    ],
    "Charrons": [
      "Nidecker H."
    ],
    "Chauffage central": [
      "Ateliers de construction Armand Pahud & Cie."
    ],
    "Chaussures (Magasins de)": [
      "Burricod Henri",
      "Gnerro Joseph",
      "Au Louvre, Magistris M., gérante",
      "Michel",
      "Zaninetti A.."
    ],
    "Chef de gare": [
      "Gay John."
    ],
    "Chef de section": [
      "Mottaz Edouard."
    ],
    "Chiffons (march. de)": [
      "Dissard Damien",
      "Revaz-Coquoz, Vve de F."
    ],
    "Cigares et tabacs": [
      "Bourgeois Jacques",
      "Brossy Eugène",
      "Gabriel Pierre",
      "Grassard",
      "Heydrich Hugo",
      "Jaccard Léon",
      "Macherich Ed.",
      "Rufenacht Th."
    ],
    "Coiffeurs, Coiffeuses": [
      "Bourgeois Jacques",
      "Dumusc Charlotte",
      "Grassard",
      "Heydrich Hugo",
      "Rochat"
    ],
    "Colonie des femmes": [
      "Une diaconesse"
    ],
    "Combustibles": [
      "Armand Pahud & Cie",
      "Demartines Louis",
      "Rod. Vve"
    ],
    "Commission scolaire": [
      "Gay John",
      "Cerez Georges",
      "Ceresole Gustave",
      "Mottaz Edouard",
      "Peter Henri",
      "Rosset Henri",
      "Rusillon Louis",
      "Schmutz Louis"
    ],
    "Commandant du 1er arrondissem": [
      "Aubert Alfred"
    ],
    "Confections": [
      "Baillif",
      "Delapierre Paul",
      "Duret frères",
      "Girardet Ernest",
      "Giroud-Gonthier Alice, Vve"
    ]
  }
}