{
  "VILLE DE LAUSANNE": {
    "INSTITUTS": [
      "Conservatoire de Lausanne",
      "Ecole Lémania (S. A.)",
      "Institut catholique",
      "Institut de musique, de Ribeaupierre",
      "Institut privé, M. Gravier"
    ],
    "INSTRUCTEURS MILITAIRES": [
      "de Muralt Henri",
      "Delessert Paul",
      "Baumann Eug.",
      "Bardet Ph.",
      "Verrey Ch.",
      "Odier Alf.",
      "Fonjallaz Arthur",
      "Jossevel Louis",
      "Secretan Isaac",
      "Schmidt Othmar",
      "Combe Gustave",
      "Friederich Ch.",
      "Bridel Georges",
      "Roussillon Jaques",
      "Collet Paul",
      "Perrenoud André",
      "Meystre Denis",
      "Mittaz Franç."
    ],
    "INSTRUMENTS DE CHIRURGIE (Fabrique de)": [
      "Hausmann (S. A.)"
    ],
    "INSTRUMENTS DE MUSIQUE Fabrique d'": [
      "Fætisch frères (S. A.)",
      "Ruchet Ch."
    ],
    "ISOLATIONS": [
      "Michoud G."
    ],
    "INVENTIONS (brevets)": [
      "Prébandier P. & Cie"
    ],
    "JOUETS": [
      "Martin & Cie"
    ],
    "JUGE D'INSTRUCTION": [
      "Blanchod Léon"
    ],
    "JUGE INFORMATEUR": [
      "Dupertuis Paul-Emile"
    ]
  }
}