{
  "LUCENS": {
    "Agriculteurs": [
      "Eugène",
      "Pichonnat",
      "Pichonnat",
      "Ballif",
      "Ballif",
      "Hrs",
      "Binggeli",
      "Bourgeois",
      "Brand",
      "Briod",
      "Cuénoud & Dubois",
      "Gavillet",
      "Michod",
      "Michod",
      "Ribet",
      "Schneider",
      "Spycher",
      "Steck",
      "Trolliet"
    ],
    "Café": [
      "Cottet"
    ],
    "Chef de section": [
      "Porchet",
      "Gros"
    ],
    "Charron": [
      "Piot",
      "Chauffard"
    ],
    "Commission scolaire": [
      "Léchaire",
      "Giroud",
      "Pidoux"
    ],
    "Cordonniers": [
      "Giroud",
      "Marti",
      "Regamey",
      "Rosset",
      "Frossard",
      "Marti",
      "Regamey",
      "Rosset",
      "Tzaud"
    ],
    "Epicerie": [
      "Germond",
      "Maillard",
      "Desarzens",
      "Gros",
      "Lezian",
      "Loup-Jordan",
      "Petitpierre",
      "Coopérative de consommation"
    ],
    "Inspecteur du bétail": [
      "Mojonnier"
    ],
    "Instituteurs": [
      "Rochat",
      "Germond"
    ],
    "Laitier": [
      "Condenserie"
    ],
    "Maréchal": [
      "Giroud"
    ],
    "Sociétés": [
      "De la fromagerie",
      "Du battoir à blé",
      "Syndicat agricole",
      "Assurance du bétail"
    ],
    "Téléphoniste": [
      "Cottet"
    ],
    "Voiturier": [
      "Rothlisberger"
    ],
    "Autorités communales": [
      "Pidoux",
      "Gasser",
      "Tanner",
      "Rey",
      "Peytregnet",
      "Lecoultre",
      "Ballif",
      "Wenger",
      "Michod"
    ],
    "Acétylène (fabr. d')": [
      "Tanner"
    ],
    "Aiguiseur": [
      "Jeanneret"
    ],
    "Assurances": [
      "La Suisse",
      "Michod"
    ],
    "Auberges et cafés": [
      "Clément",
      "Crausaz",
      "Grand",
      "Holzer",
      "Maillard",
      "Maillard",
      "Jaunin",
      "Pluviaux",
      "Savio",
      "Vanev",
      "Maillard"
    ],
    "Banque": [
      "Crédit Mutuel de Lucens (S. A.)"
    ],
    "Bière (dépôt de)": [
      "Grande Brasserie Beauregard",
      "Dépôt de la Brasserie du Cardinal"
    ],
    "Blanchisseuse-repasseuse": [
      "Strikler"
    ],
    "Bois (march. de)": [
      "Michod",
      "Trolliet",
      "Vaney"
    ],
    "Bouchers": [
      "Favre",
      "fils",
      "Boucherie sociale",
      "Charles"
    ],
    "Boulangers": [
      "Ganty",
      "Luder-Krummen",
      "Michod",
      "hoirs d'Ed.",
      "Reymond"
    ],
    "Cafés-chocolat": [
      "Degoumois-Favrat"
    ],
    "Cercueils": [
      "Hessenmüller",
      "Genton",
      "Chévallaz, S. A., Lausanne",
      "Leuba"
    ],
    "Cigares et tabacs": [
      "Huwiler"
    ],
    "Chapellerie": [
      "Meyer"
    ],
    "Charcuteries": [
      "Favre",
      "fils",
      "Charles"
    ],
    "Chaussures": [
      "Regamey",
      "Rosset"
    ],
    "Chaux et ciments": [
      "Ferrini",
      "Zaretti"
    ],
    "Chef de gare": [
      "Augsburgër"
    ],
    "Coiffeurs": [
      "Gros",
      "Maag",
      "Potterat"
    ],
    "Commandant du feu": [
      "Tanner"
    ],
    "Constructeurs-mécaniciens": [
      "Jornod",
      "Tanner"
    ],
    "Draperie": [
      "Meyer"
    ],
    "Droguerie": [
      "Lezian"
    ],
    "Electricien": [
      "Rapaz"
    ],
    "Engrais chimiques": [
      "Société d'agriculture",
      "Tanner",
      "Zaretti"
    ],
    "Entrepreneurs": [
      "Camélia & Casoto",
      "Ferrini-Durussel",
      "Zaretti"
    ],
    "Facteurs": [
      "Bourgeois",
      "Cheseaux",
      "Cheseaux",
      "Strikler",
      "fils"
    ]
  }
}