{
  "YVERDON": {
    "Nickelage et chromage": [
      "Fabrique suisse de vis et boulons",
      "Paillard E. & Cie, S. A.",
      "Leclanché S. A.",
      "Reymond Albert"
    ],
    "Notaires": [
      "Courvoisier Aimé",
      "Decker Charles",
      "Michaud André",
      "Pilloud John",
      "Schmidhauser Marcel",
      "Servien Prosper et Louis"
    ],
    "Opticiens": [
      "Baehler Marguerite",
      "Piaget Adèle",
      "Schwarz-Gloor Emile",
      "Wehrli Alfred"
    ],
    "Papiers peints": [
      "Antoniotti A.",
      "Baatard Henri",
      "Dubath Ch.",
      "Mutrux René",
      "Vagnières J.",
      "Vetter Emile"
    ],
    "Parapluies (fab. de)": [
      "Chapuis Henri"
    ],
    "Paratonnerres": [
      "Baumann Albert"
    ],
    "Parquets (fournit. et pose de)": [
      "Cheya S. A.",
      "Gloor André"
    ],
    "Pâtes alimentaires (fabr. de)": [
      "Besson G. & Cie"
    ],
    "Pêche (articles de)": [
      "Brasey Louis",
      "Henrioud René",
      "Musy Aimé"
    ],
    "Pédicures": [
      "Butticaz, Mlle",
      "Collomb S., Mme",
      "Favre Georges",
      "Gonin Marcel",
      "Matthey, Mme",
      "Ray V., Mlle"
    ],
    "Peintres (voir aussi Gypsiers)": [
      "Loup James"
    ],
    "Peintre en voitures": [
      "Michel frères"
    ],
    "Pensions": [
      "Briod Marcel",
      "Collet René",
      "Cordier Philippe",
      "Cornu-Baumann M.",
      "Demiéville, Vve",
      "Paris, Mlle",
      "Payot M., Vve",
      "Prahin Henri"
    ],
    "Pensionnats": [
      "Cand-Chapuis, Mme et M.",
      "Ecole Duployé",
      "Marendaz Suzanne"
    ],
    "Pépiniériste": [
      "Pury René",
      "Sermet Maurice",
      "Theubet Jules",
      "von Gunten Jules"
    ],
    "Pharmaciens": [
      "Delay Gaston",
      "Kasser Georges",
      "Perret Georges",
      "Perret",
      "Pharmacie Centrale, Sandoz Roger",
      "Piguet V."
    ],
    "Pharmacie (produits pour)": [
      "Cepha S. A.",
      "Petitat A. G.",
      "Laboratoire pharmaceutique Gedy S.A."
    ],
    "Photographes": [
      "Benner Th.",
      "Duperrex Paul",
      "Ferret Alfred",
      "Pérusset J.",
      "Petitpierre Myrette",
      "Spahlinger René et fils"
    ],
    "Photographie (art. pour la)": [
      "Duperrex Paul",
      "Läuchli Hans",
      "Perret Alfred",
      "Pharmacie Centrale",
      "Spahlinger R."
    ],
    "Pierres fines": [
      "Degoumois Roger",
      "Michoud A.",
      "Moser Ernest",
      "Portmann Alb.",
      "Sueur Arthur",
      "Vermot Marcel",
      "Watch-Jewels Co, Ltd Export"
    ],
    "Piles électriques (fab. de)": [
      "S. A. Leclanché"
    ],
    "Poêliers-fumistes": [
      "Bercher Joseph",
      "Montandon Arm."
    ],
    "Pompes funèbres": [
      "Geneux Emile",
      "Wuille Aug.",
      "Pompes funèbres du Nord, Schulz Paul"
    ],
    "Porcelaine et verrerie": [
      "Cochet Sophie",
      "Dubath André",
      "Henriod-Giddey Emile",
      "Kueny Albert",
      "Walther-Bloch (les fils)"
    ],
    "Porcs (march. de)": [
      "Genillod Juste",
      "Grossenbacher Albert",
      "Martinet Gabriel",
      "Richard Ernest"
    ],
    "Primeurs": [
      "Cand Robert",
      "Capelli Marius fils",
      "Galmès frères",
      "Giroud Valentin",
      "Losio, Mme",
      "Pavid Frédéric",
      "Peguiron frères",
      "Specht Louis",
      "Wagnières Délia"
    ],
    "Produits chimiques": [
      "Chimie Agricole S. A.",
      "Etablissem. Vimosin S. A.",
      "Neiger Alfred"
    ],
    "Produits en ciment": [
      "Fabrique de produits en ciment S. A."
    ],
    "Professeurs de langues": [
      "Frattini C.",
      "Margot Henriette",
      "Roussel Paul, Mme"
    ],
    "Professeurs de sténographie": [
      "Cand, Mme",
      "Delorme J., Mlle",
      "Mutrux René",
      "Rouillier Isabelle"
    ],
    "Professeurs de musique": [
      "Bollier Elsa",
      "Coderay F.",
      "Godard Ph.-Jules",
      "Hoog Sœurs",
      "Institut Benda",
      "Jaccard-Meylan, Mme",
      "Kaser Irène",
      "Marendaz Simone",
      "Ochsner",
      "Pahud Isabelle",
      "Perey M.",
      "Piaget Alfred",
      "Saugy Marie-Lse",
      "Société du Conservatoire et Institut de Musique",
      "Spada-Verdan Louise"
    ],
    "Quincaillerie": [
      "Carrel L. et C.",
      "Dubath André",
      "Freymond Adr.",
      "Kueny Albert",
      "Mottaz frères",
      "Pillevuit Emile",
      "Simoncini Etienne"
    ],
    "Radio-Gramo": [
      "Equipement électrique S. A.",
      "Félix G.",
      "Jeanneret André",
      "Leclanché S.A.",
      "Lutz A.",
      "Paillard E. & Cie",
      "Vagnières Jules",
      "Wehrli Alfred",
      "Wyss Richard"
    ]
  }
}