{
  "RENENS": {
    "SCULPTEURS": [
      "Allenspach A.",
      "Battilotti Angelo",
      "Besse Robert",
      "Bourgoz César",
      "Gailloud André",
      "Martin-Odot Milo",
      "Pettineroli André",
      "Roncatti Georges",
      "Schlageter Arthur",
      "Simecek François",
      "Tommasini L. & Rinaldi",
      "Uberti L. & H."
    ],
    "SECHAGE PAR ABSORPTION": [
      "FIR S. A."
    ],
    "SECRÉTAIRES": [
      "Secrétariat antialcoolique",
      "Oettli Max",
      "Secrétariat romand d'hygiène sociale et morale",
      "Veillard Maurice"
    ],
    "SELLIERS": [
      "Droz Achille",
      "Froehly Jos.",
      "Grau Fritz",
      "Trosch Otto"
    ],
    "SERRURIERS": [
      "Baudet Aug.",
      "Blanc André",
      "Brauchli Willy",
      "Briod Ernest",
      "Canova E.",
      "Gandolfi Marie",
      "Gerottini Fr.",
      "Chapuis Louis",
      "Clerc Henri",
      "Décosterd Henri fils",
      "Desclouds Aloïs",
      "Droguet Jean",
      "Duboux Henri",
      "Elsasser Ch.",
      "Erbs W.",
      "Essenti Jules",
      "Félix Robert",
      "Fiaux Roger",
      "Fuchs Jean",
      "Gassmann Th.",
      "Gentizon Alf.",
      "Gotti Charles",
      "Gujer Henri",
      "Haas Emile",
      "Hammer Walther",
      "Jaccottet Arthur",
      "Lavenez Henri",
      "Mahon Armand",
      "Margot Louis",
      "Marti Henri",
      "Maurer Ed.",
      "Melliger-Bourgoz Jacob",
      "Minazoli Victor",
      "Muller Charles",
      "Nobs Félix",
      "Nydegger Fréd.",
      "Pache Paul",
      "Peretti Victor",
      "PERRET FRÈRES",
      "Ramalet frères S. A.",
      "Ramseyer Jean",
      "Rossat & Blanc",
      "Rubli Fernand",
      "Savaré Jean",
      "Schmidt Marcel",
      "Seiler Théodore",
      "Spagnol A., S. A.",
      "Tauxe François",
      "Thélin Armand",
      "Tribolet Paul",
      "Viret Henri et fils",
      "Zwahlen & Mayr"
    ],
    "SERVICE D'ESCOMPTE": [
      "Association des Commerçants Lausannois"
    ]
  }
}